doublemanning/ForwardModel.py
doublemanning/ManningFit.py
doublemanning/__init__.py
doublemanning/_version.py
doublemanning/cli.py
doublemanning-1.0.0a0.dist-info/LICENSE
doublemanning-1.0.0a0.dist-info/METADATA
doublemanning-1.0.0a0.dist-info/WHEEL
doublemanning-1.0.0a0.dist-info/entry_points.txt
doublemanning-1.0.0a0.dist-info/top_level.txt
doublemanning-1.0.0a0.dist-info/RECORD
