Metadata-Version: 2.1
Name: doublemanning
Version: 1.0.0a0
Summary: Stage-discharge relationships: double-Manning approach
Home-page: https://github.com/MNiMORPH/rating-curve-2x-manning/
Author: Andrew D. Wickert
Author-email: awickert@umn.edu
Project-URL: Model page, https://csdms.colorado.edu/wiki/Model:GRLP
Keywords: fluvial geomorphology sediment transport landscape evolution
Classifier: Programming Language :: Python :: 3
Classifier: License :: OSI Approved :: GNU General Public License v3 (GPLv3)
Classifier: Operating System :: OS Independent
Classifier: Topic :: Scientific/Engineering :: Hydrology
Classifier: Intended Audience :: Science/Research
License-File: LICENSE
Requires-Dist: pandas
Requires-Dist: numpy
Requires-Dist: scipy
Requires-Dist: matplotlib
Requires-Dist: scikit-learn
